protofcp/FCPSocket.py
protofcp/__init__.py
protofcp/assemblr.py
protofcp/consts.py
protofcp/disassemblr.py
protofcp-0.0.4.dist-info/LICENSE
protofcp-0.0.4.dist-info/METADATA
protofcp-0.0.4.dist-info/WHEEL
protofcp-0.0.4.dist-info/top_level.txt
protofcp-0.0.4.dist-info/RECORD
