Metadata-Version: 2.1
Name: protofcp
Version: 0.0.4
Summary: FCP is a protocol used to route on "channels" and send or receive data.
Home-page: https://github.com/ANDRVV/FCP
Author: Andrea Vaccaro
License: Apache 2.0
Keywords: python,socket,protocol,proto,channel,scapy,packet
Classifier: Development Status :: 1 - Planning
Classifier: Intended Audience :: Developers
Classifier: Programming Language :: Python :: 3
Classifier: Operating System :: Unix
Classifier: Operating System :: MacOS :: MacOS X
Classifier: Operating System :: Microsoft :: Windows
License-File: LICENSE
Requires-Dist: scapy
